evo_science/__init__.py
evo_science/__main__.py
evo_science/base.py
evo_science/cli.py
evo_science/config.py
evo_science/metric_lib.py
evo_science/entities/__init__.py
evo_science/entities/evs_logger.py
evo_science/entities/features/__init__.py
evo_science/entities/features/base_feature.py
evo_science/entities/features/feature_set.py
evo_science/entities/features/feature_types.py
evo_science/entities/metrics/__init__.py
evo_science/entities/metrics/accuracy.py
evo_science/entities/metrics/auc.py
evo_science/entities/metrics/base_binary_classify_metric.py
evo_science/entities/metrics/base_metric.py
evo_science/entities/metrics/error_ave.py
evo_science/entities/metrics/error_std.py
evo_science/entities/metrics/f1_score.py
evo_science/entities/metrics/intercept.py
evo_science/entities/metrics/mae.py
evo_science/entities/metrics/mse.py
evo_science/entities/metrics/precision.py
evo_science/entities/metrics/r_squared.py
evo_science/entities/metrics/recall.py
evo_science/entities/metrics/rmse.py
evo_science/entities/metrics/roc_curve.py
evo_science/entities/metrics/slope.py
evo_science/entities/metrics/wape.py
evo_science/entities/models/__init__.py
evo_science/entities/models/base_model.py
evo_science/entities/models/decision_tree.py
evo_science/entities/models/linear_regression_model.py
evo_science/entities/models/logistic_regression_model.py
evo_science/entities/models/xg_boost.py
evo_science-0.1.14.dist-info/LICENSE
evo_science-0.1.14.dist-info/METADATA
evo_science-0.1.14.dist-info/WHEEL
evo_science-0.1.14.dist-info/entry_points.txt
evo_science-0.1.14.dist-info/top_level.txt
evo_science-0.1.14.dist-info/RECORD
