Metadata-Version: 2.1
Name: evo-science
Version: 0.1.14
Summary: Awesome evo_science created by maycuatroi
Home-page: https://github.com/maycuatroi/evo-science/
Author: maycuatroi
License-File: LICENSE
Requires-Dist: scikit-learn
Requires-Dist: matplotlib
Requires-Dist: xgboost
Requires-Dist: dtreeviz
Requires-Dist: tabulate
Requires-Dist: seaborn
Requires-Dist: pandas
Requires-Dist: python-dotenv
Provides-Extra: keras
Requires-Dist: jax[cuda12_pip] ; extra == 'keras'
Requires-Dist: keras ; extra == 'keras'
Provides-Extra: test
Requires-Dist: pytest ; extra == 'test'
Requires-Dist: coverage ; extra == 'test'
Requires-Dist: flake8 ; extra == 'test'
Requires-Dist: black ; extra == 'test'
Requires-Dist: isort ; extra == 'test'
Requires-Dist: pytest-cov ; extra == 'test'
Requires-Dist: codecov ; extra == 'test'
Requires-Dist: mypy ; extra == 'test'
Requires-Dist: gitchangelog ; extra == 'test'
Requires-Dist: mkdocs ; extra == 'test'
